resnet_pytorch/__init__.py
resnet_pytorch/model.py
resnet_pytorch/utils.py
resnet_pytorch-0.2.0.dist-info/LICENSE
resnet_pytorch-0.2.0.dist-info/METADATA
resnet_pytorch-0.2.0.dist-info/WHEEL
resnet_pytorch-0.2.0.dist-info/top_level.txt
resnet_pytorch-0.2.0.dist-info/RECORD
